argonaut/__init__.py
argonaut/arguments.py
argonaut/core.py
argonaut/decorators.py
argonaut/exceptions.py
argonaut/fancy_output.py
argonaut/input_sanitizer.py
argonaut/logging.py
argonaut/plugins.py
argonaut/shell_completion.py
argonaut/utils.py
argon4ut_cli-0.3.1.dist-info/LICENSE.md
argon4ut_cli-0.3.1.dist-info/METADATA
argon4ut_cli-0.3.1.dist-info/WHEEL
argon4ut_cli-0.3.1.dist-info/top_level.txt
argon4ut_cli-0.3.1.dist-info/RECORD
