Metadata-Version: 2.1
Name: argon4ut-cli
Version: 0.3.1
Summary: A custom argument parsing library for CLI applications with a focus on simplicity and ease of use. ArgøNaut is designed to make it easy to create powerful and flexible command-line interfaces.
Home-page: https://github.com/sc4rfurry/argon4ut
Author: sc4rfurry
Author-email: akalucifr@protonmail.ch
Classifier: Programming Language :: Python :: 3
Classifier: License :: OSI Approved :: MIT License
Classifier: Operating System :: OS Independent
Requires-Python: >=3.6
License-File: LICENSE.md
Requires-Dist: pyyaml
Provides-Extra: test
Requires-Dist: pytest; extra == "test"
Requires-Dist: pytest-cov; extra == "test"
